{
    "Tier_6_Conservative_N_eq_M_64": {
        "description": "Conservative config with N = M = 64 (4096 dot products)",
        "mul_lanes": 64,
        "mul_cols": 64,
        "bit_precision": 4,
        "bit_rate": 1,
        "max_parallel_dotprods": 4096,
        "p_out_per_lane": -22.1,
        "pd_threshold": -22.0,
        "topology": "N=M",
        "organization": "MWA",
        "tier": "Tier_6",
        "sources": [
            "Derived from PIDCOP scalability CSV (digital_pidcop_dr_sensitive_results.csv), 1 GS/s, Bit=4, Max N or M=146"
        ],
        "energy_per_mac": {
            "value": 2e-13,
            "unit": "J",
            "source": "Holylight paper (https://past.date-conference.com/proceedings-archive/2019/pdf/0156.pdf)"
        },
        "adc_energy_per_conv": {
            "value": 1e-12,
            "unit": "J",
            "source": "Bangari et al., DEAP-CNN (https://www.queensu.ca/physics/shastrilab/sites/shastwww/files/uploaded_files/publications/journals/56_Bangari_JSTQE_deap_2020.pdf)"
        },
        "dac_energy_per_bit": {
            "value": 5e-13,
            "unit": "J",
            "source": "Silicon photonics DAC survey (typical CMOS-integrated DAC energy)"
        },
        "static_power": {
            "value": 0.05,
            "unit": "W",
            "source": "Estimated based on laser biasing and thermal tuning losses (Holylight, Lightbulb papers)"
        },
        "area_per_mul_lane": {
            "value": 0.005,
            "unit": "mm^2",
            "source": "Lightbulb and PIXEL layout projections (https://hpcat.seas.gwu.edu/assets/files/PIXEL_Photonic_Neural_Network_Accelerator.pdf)"
        },
        "pca_area": {
            "value": 0.01,
            "unit": "mm^2",
            "source": "DEAP-CNN architecture and layout (Bangari et al.)"
        },
        "adc_area": {
            "value": 0.002,
            "unit": "mm^2",
            "source": "Low-power ADC design surveys at 28\u201365nm"
        },
        "waveguide_pitch": {
            "value": 0.02,
            "unit": "mm",
            "source": "Standard silicon photonic WDM spacing from Lightbulb/PIXEL papers"
        },
        "reuse_factor": {
            "value": 8,
            "source": "Assumed based on common reuse in systolic/photonic accelerator design"
        }
    },
    "Tier_6_Max_N_eq_M_146": {
        "description": "Max performance config with N = M = 146 (21316 dot products)",
        "mul_lanes": 146,
        "mul_cols": 146,
        "bit_precision": 4,
        "bit_rate": 1,
        "max_parallel_dotprods": 21316,
        "p_out_per_lane": -22.1,
        "pd_threshold": -22.0,
        "topology": "N=M",
        "organization": "MWA",
        "tier": "Tier_6",
        "sources": [
            "Derived from PIDCOP scalability CSV (digital_pidcop_dr_sensitive_results.csv), 1 GS/s, Bit=4, Max N or M=146"
        ],
        "energy_per_mac": {
            "value": 2e-13,
            "unit": "J",
            "source": "Holylight paper (https://past.date-conference.com/proceedings-archive/2019/pdf/0156.pdf)"
        },
        "adc_energy_per_conv": {
            "value": 1e-12,
            "unit": "J",
            "source": "Bangari et al., DEAP-CNN (https://www.queensu.ca/physics/shastrilab/sites/shastwww/files/uploaded_files/publications/journals/56_Bangari_JSTQE_deap_2020.pdf)"
        },
        "dac_energy_per_bit": {
            "value": 5e-13,
            "unit": "J",
            "source": "Silicon photonics DAC survey (typical CMOS-integrated DAC energy)"
        },
        "static_power": {
            "value": 0.05,
            "unit": "W",
            "source": "Estimated based on laser biasing and thermal tuning losses (Holylight, Lightbulb papers)"
        },
        "area_per_mul_lane": {
            "value": 0.005,
            "unit": "mm^2",
            "source": "Lightbulb and PIXEL layout projections (https://hpcat.seas.gwu.edu/assets/files/PIXEL_Photonic_Neural_Network_Accelerator.pdf)"
        },
        "pca_area": {
            "value": 0.01,
            "unit": "mm^2",
            "source": "DEAP-CNN architecture and layout (Bangari et al.)"
        },
        "adc_area": {
            "value": 0.002,
            "unit": "mm^2",
            "source": "Low-power ADC design surveys at 28\u201365nm"
        },
        "waveguide_pitch": {
            "value": 0.02,
            "unit": "mm",
            "source": "Standard silicon photonic WDM spacing from Lightbulb/PIXEL papers"
        },
        "reuse_factor": {
            "value": 8,
            "source": "Assumed based on common reuse in systolic/photonic accelerator design"
        }
    },
    "Tier_6_Asymmetric_N_32_M_64": {
        "description": "Asymmetric config with N=32, M=64 (2048 dot products)",
        "mul_lanes": 32,
        "mul_cols": 64,
        "bit_precision": 4,
        "bit_rate": 1,
        "max_parallel_dotprods": 2048,
        "p_out_per_lane": -22.1,
        "pd_threshold": -22.0,
        "topology": "N\u2260M",
        "organization": "MWA",
        "tier": "Tier_6",
        "sources": [
            "Derived from PIDCOP scalability CSV (digital_pidcop_dr_sensitive_results.csv), 1 GS/s, Bit=4, Max N or M=146"
        ],
        "energy_per_mac": {
            "value": 2e-13,
            "unit": "J",
            "source": "Holylight paper (https://past.date-conference.com/proceedings-archive/2019/pdf/0156.pdf)"
        },
        "adc_energy_per_conv": {
            "value": 1e-12,
            "unit": "J",
            "source": "Bangari et al., DEAP-CNN (https://www.queensu.ca/physics/shastrilab/sites/shastwww/files/uploaded_files/publications/journals/56_Bangari_JSTQE_deap_2020.pdf)"
        },
        "dac_energy_per_bit": {
            "value": 5e-13,
            "unit": "J",
            "source": "Silicon photonics DAC survey (typical CMOS-integrated DAC energy)"
        },
        "static_power": {
            "value": 0.05,
            "unit": "W",
            "source": "Estimated based on laser biasing and thermal tuning losses (Holylight, Lightbulb papers)"
        },
        "area_per_mul_lane": {
            "value": 0.005,
            "unit": "mm^2",
            "source": "Lightbulb and PIXEL layout projections (https://hpcat.seas.gwu.edu/assets/files/PIXEL_Photonic_Neural_Network_Accelerator.pdf)"
        },
        "pca_area": {
            "value": 0.01,
            "unit": "mm^2",
            "source": "DEAP-CNN architecture and layout (Bangari et al.)"
        },
        "adc_area": {
            "value": 0.002,
            "unit": "mm^2",
            "source": "Low-power ADC design surveys at 28\u201365nm"
        },
        "waveguide_pitch": {
            "value": 0.02,
            "unit": "mm",
            "source": "Standard silicon photonic WDM spacing from Lightbulb/PIXEL papers"
        },
        "reuse_factor": {
            "value": 8,
            "source": "Assumed based on common reuse in systolic/photonic accelerator design"
        }
    }
}